odoo8_addon_project_issue_task-8.0.1.1.0.99.dev37-py3.8-nspkg.pth
odoo_addons/project_issue_task/__init__.py
odoo_addons/project_issue_task/__openerp__.py
odoo_addons/project_issue_task/project_issue.py
odoo_addons/project_issue_task/project_issue_view.xml
odoo_addons/project_issue_task/project_task.py
odoo_addons/project_issue_task/project_task_cause.py
odoo_addons/project_issue_task/project_task_cause_view.xml
odoo_addons/project_issue_task/project_task_view.xml
odoo_addons/project_issue_task/i18n/am.po
odoo_addons/project_issue_task/i18n/ar.po
odoo_addons/project_issue_task/i18n/bg.po
odoo_addons/project_issue_task/i18n/bs.po
odoo_addons/project_issue_task/i18n/ca.po
odoo_addons/project_issue_task/i18n/ca_ES.po
odoo_addons/project_issue_task/i18n/cs.po
odoo_addons/project_issue_task/i18n/da.po
odoo_addons/project_issue_task/i18n/da_DK.po
odoo_addons/project_issue_task/i18n/de.po
odoo_addons/project_issue_task/i18n/el.po
odoo_addons/project_issue_task/i18n/el_GR.po
odoo_addons/project_issue_task/i18n/en_GB.po
odoo_addons/project_issue_task/i18n/es.po
odoo_addons/project_issue_task/i18n/es_AR.po
odoo_addons/project_issue_task/i18n/es_CL.po
odoo_addons/project_issue_task/i18n/es_CO.po
odoo_addons/project_issue_task/i18n/es_CR.po
odoo_addons/project_issue_task/i18n/es_DO.po
odoo_addons/project_issue_task/i18n/es_EC.po
odoo_addons/project_issue_task/i18n/es_ES.po
odoo_addons/project_issue_task/i18n/es_MX.po
odoo_addons/project_issue_task/i18n/es_PE.po
odoo_addons/project_issue_task/i18n/es_PY.po
odoo_addons/project_issue_task/i18n/es_VE.po
odoo_addons/project_issue_task/i18n/et.po
odoo_addons/project_issue_task/i18n/fa.po
odoo_addons/project_issue_task/i18n/fi.po
odoo_addons/project_issue_task/i18n/fr.po
odoo_addons/project_issue_task/i18n/fr_CA.po
odoo_addons/project_issue_task/i18n/fr_CH.po
odoo_addons/project_issue_task/i18n/gl.po
odoo_addons/project_issue_task/i18n/gl_ES.po
odoo_addons/project_issue_task/i18n/he.po
odoo_addons/project_issue_task/i18n/hr.po
odoo8_addon_project_issue_task-8.0.1.1.0.99.dev37.dist-info/METADATA
odoo8_addon_project_issue_task-8.0.1.1.0.99.dev37.dist-info/WHEEL
odoo8_addon_project_issue_task-8.0.1.1.0.99.dev37.dist-info/namespace_packages.txt
odoo8_addon_project_issue_task-8.0.1.1.0.99.dev37.dist-info/top_level.txt
odoo8_addon_project_issue_task-8.0.1.1.0.99.dev37.dist-info/RECORD
